leads_jarvis/__entry__.py
leads_jarvis/__init__.py
leads_jarvis/__main__.py
leads_jarvis/cli.py
leads_jarvis/dataset.py
leads_jarvis/trainer.py
leads_jarvis/utils.py
leads_jarvis/checkpoints/rrs.pth
leads_jarvis/checkpoints/yolov8m.pt
leads_jarvis/checkpoints/yolov8n.pt
leads_jarvis/checkpoints/yolov8s.pt
leads_jarvis/network/__init__.py
leads_jarvis/network/friday.py
leads_jarvis/network/vit.py
leads_jarvis/network/detection/__init__.py
leads_jarvis/network/detection/prototype.py
leads_jarvis/network/detection/yolo.py
leads_jarvis/network/segmentation/__init__.py
leads_jarvis/network/segmentation/prototype.py
leads_jarvis/network/segmentation/rrs.py
leads_jarvis/network/segmentation/sam.py
leads_jarvis-0.0.1.dist-info/METADATA
leads_jarvis-0.0.1.dist-info/WHEEL
leads_jarvis-0.0.1.dist-info/entry_points.txt
leads_jarvis-0.0.1.dist-info/RECORD
